[
    {
        "id":1,
        "nazva":"Тірамісу",
        "opis":"Класичний італійський десерт з кави",
        "tsina":"120.00",
        "vaha_gram":150,
        "dostupnyy":true,
        "kategoria":"Торти",
        "foto_url":"/foto_deserts/tiramisu.jpg"
    },
    {
        "id":2,
        "nazva":"Чізкейк Нью-Йорк",
        "opis":"Ніжний сирний десерт на основі вершкового сиру",
        "tsina":"110.00",
        "vaha_gram":120,
        "dostupnyy":true,
        "kategoria":"Торти",
        "foto_url":"/foto_deserts/new_york_cheesecake.jpg"
    },
    {
        "id":3,
        "nazva":"Макарун",
        "opis":"Французький мигдалевий печиво з начинкою",
        "tsina":"35.00",
        "vaha_gram":25,
        "dostupnyy":true,
        "kategoria":"Печиво",
        "foto_url":"/foto_deserts/makaruns.jpg"
    },
    {
        "id":4,
        "nazva":"Круасан з мигдалем",
        "opis":"Смачний випічка з мигдалевою начинкою",
        "tsina":"45.00",
        "vaha_gram":80,
        "dostupnyy":true,
        "kategoria":"Випічка",
        "foto_url":"/foto_deserts/kruasan_migdal.jpg"
    },
    {
        "id":5,
        "nazva":"Шоколадний фондан",
        "opis":"Теплий шоколадний кекс з рідкою серединкою",
        "tsina":"95.00",
        "vaha_gram":100,
        "dostupnyy":true,
        "kategoria":"Десерти",
        "foto_url":"/foto_deserts/chocolate_fondan.jpg"
    }
]